mercury_parser/__init__.py
mercury_parser/client.py
mercury_parserpy-0.7.0.dist-info/LICENSE
mercury_parserpy-0.7.0.dist-info/METADATA
mercury_parserpy-0.7.0.dist-info/WHEEL
mercury_parserpy-0.7.0.dist-info/top_level.txt
mercury_parserpy-0.7.0.dist-info/RECORD
