Metadata-Version: 2.1
Name: mercury-parserpy
Version: 0.7.0
Summary: UNKNOWN
Home-page: https://github.com/Girbons/mercury-parserpy
Author: Alessandro De Angelis
Author-email: alessandrodea22@gmail.com
License: MIT
Platform: UNKNOWN
License-File: LICENSE
Requires-Dist: requests
